README.md
setup.cfg
setup.py
pyslock/__init__.py
pyslock/client.py
pyslock/connection.py
pyslock/database.py
pyslock/event.py
pyslock/lock.py
pyslock/reader.py
pyslock/rlock.py
pyslock/rwlock.py
pyslock/semaphore.py
pyslock/utils.py
pyslock.egg-info/PKG-INFO
pyslock.egg-info/SOURCES.txt
pyslock.egg-info/dependency_links.txt
pyslock.egg-info/not-zip-safe
pyslock.egg-info/top_level.txt
pyslock/asyncio/__init__.py
pyslock/asyncio/client.py
pyslock/asyncio/connection.py
pyslock/asyncio/database.py
pyslock/asyncio/event.py
pyslock/asyncio/lock.py
pyslock/asyncio/rlock.py
pyslock/asyncio/rwlock.py
pyslock/asyncio/semaphore.py
pyslock/protocol/__init__.py
pyslock/protocol/command.py
pyslock/protocol/exceptions.py
pyslock/protocol/result.py