Metadata-Version: 2.1
Name: pyslock
Version: 0.0.1
Summary: High-performance distributed shared lock service client driver
Home-page: https://github.com/snower/pyslock
Author: snower
Author-email: sujian199@gmail.com
License: MIT
Keywords: shared lock,slock
Platform: UNKNOWN
